{
    "name": "XML Formatter",
    "description": "A web-based tool for formatting XML content. Allows users to input XML code, format it with proper indentation, copy formatted XML, download it as a file, and clear the input/output areas. Built using HTML, CSS (Tailwind CSS), and JavaScript.",
    "contributors": [{
        "name": "Masum Ahmed",
        "githubId": "ri-masum"
    }, {
        "name": "Enamur Rabbi Ferdausi ",
        "githubId": "EnamurFerdausi"
    },
    {
        "name": "Nikhil Sarve",
        "githubId": "nikhilsarve"
    },
    {
        "name": "Akash Gaikwad",
        "githubId": "sky-gaikwad "
    },
    {
        "name": "Atharva Thakur",
        "githubId": "plantindesk"
    }]
}